{
  "coverage": "61.9%",
  "expectCount": 42,
  "actualCount": 26,
  "files": {
    "js/analyze/index.js": {
      "expectCount": 1,
      "actualCount": 0,
      "undocumentLines": [
        3
      ]
    },
    "js/analyze/plugin/0003_CJRC.js": {
      "expectCount": 1,
      "actualCount": 0,
      "undocumentLines": [
        1
      ]
    },
    "js/analyze/plugin/8D3F_Kururu.js": {
      "expectCount": 5,
      "actualCount": 0,
      "undocumentLines": [
        3,
        18,
        30,
        48,
        61
      ]
    },
    "js/analyze/plugin/index.js": {
      "expectCount": 1,
      "actualCount": 1,
      "undocumentLines": []
    },
    "js/FelicaCmd.js": {
      "expectCount": 1,
      "actualCount": 1,
      "undocumentLines": []
    },
    "js/JsRNFelica.js": {
      "expectCount": 30,
      "actualCount": 22,
      "undocumentLines": [
        7,
        8,
        56,
        146,
        149,
        152,
        155,
        530
      ]
    },
    "js/Util.js": {
      "expectCount": 3,
      "actualCount": 2,
      "undocumentLines": [
        1
      ]
    }
  }
}